openlit/__helpers.py
openlit/__init__.py
openlit/_instrumentors.py
openlit/cli/__init__.py
openlit/cli/bootstrap/sitecustomize.py
openlit/cli/config.py
openlit/cli/main.py
openlit/evals/__init__.py
openlit/evals/all.py
openlit/evals/bias_detection.py
openlit/evals/hallucination.py
openlit/evals/toxicity.py
openlit/evals/utils.py
openlit/guard/__init__.py
openlit/guard/all.py
openlit/guard/prompt_injection.py
openlit/guard/restrict_topic.py
openlit/guard/sensitive_topic.py
openlit/guard/utils.py
openlit/instrumentation/ag2/__init__.py
openlit/instrumentation/ag2/ag2.py
openlit/instrumentation/ag2/async_ag2.py
openlit/instrumentation/ag2/utils.py
openlit/instrumentation/agno/__init__.py
openlit/instrumentation/agno/agno.py
openlit/instrumentation/agno/async_agno.py
openlit/instrumentation/agno/utils.py
openlit/instrumentation/ai21/__init__.py
openlit/instrumentation/ai21/ai21.py
openlit/instrumentation/ai21/async_ai21.py
openlit/instrumentation/ai21/utils.py
openlit/instrumentation/anthropic/__init__.py
openlit/instrumentation/anthropic/anthropic.py
openlit/instrumentation/anthropic/async_anthropic.py
openlit/instrumentation/anthropic/utils.py
openlit/instrumentation/assemblyai/__init__.py
openlit/instrumentation/assemblyai/assemblyai.py
openlit/instrumentation/assemblyai/utils.py
openlit/instrumentation/astra/__init__.py
openlit/instrumentation/astra/astra.py
openlit/instrumentation/astra/async_astra.py
openlit/instrumentation/astra/utils.py
openlit/instrumentation/azure_ai_inference/__init__.py
openlit/instrumentation/azure_ai_inference/async_azure_ai_inference.py
openlit/instrumentation/azure_ai_inference/azure_ai_inference.py
openlit/instrumentation/azure_ai_inference/utils.py
openlit/instrumentation/bedrock/__init__.py
openlit/instrumentation/bedrock/bedrock.py
openlit/instrumentation/bedrock/utils.py
openlit/instrumentation/browser_use/__init__.py
openlit/instrumentation/browser_use/async_browser_use.py
openlit/instrumentation/browser_use/browser_use.py
openlit-1.36.3.dist-info/METADATA
openlit-1.36.3.dist-info/WHEEL
openlit-1.36.3.dist-info/entry_points.txt
openlit-1.36.3.dist-info/licenses/LICENSE
openlit-1.36.3.dist-info/RECORD
