Metadata-Version: 2.4
Name: openlit
Version: 1.36.3
Summary: OpenTelemetry-native Auto instrumentation library for monitoring LLM Applications and GPUs, facilitating the integration of observability into your GenAI-driven projects
License: Apache-2.0
License-File: LICENSE
Keywords: OpenTelemetry,otel,otlp,llm,tracing,openai,anthropic,claude,cohere,llm monitoring,observability,monitoring,gpt,Generative AI,chatGPT,gpu
Author: OpenLIT
Requires-Python: >=3.9.0,<4.0.0
Classifier: License :: OSI Approved :: Apache Software License
Classifier: Programming Language :: Python :: 3
Classifier: Programming Language :: Python :: 3.9
Classifier: Programming Language :: Python :: 3.10
Classifier: Programming Language :: Python :: 3.11
Classifier: Programming Language :: Python :: 3.12
Classifier: Programming Language :: Python :: 3.13
Classifier: Programming Language :: Python :: 3.14
Requires-Dist: anthropic (>=0.42.0,<1.0.0)
Requires-Dist: boto3 (>=1.34.0,<2.0.0)
Requires-Dist: botocore (>=1.34.0,<2.0.0)
Requires-Dist: langchain (>=0.3.15,<0.4.0)
Requires-Dist: openai (>=1.1.1,<2.0.0)
Requires-Dist: openai-agents (>=0.0.3)
Requires-Dist: opentelemetry-api (>=1.30.0,<2.0.0)
Requires-Dist: opentelemetry-exporter-otlp (>=1.30.0,<2.0.0)
Requires-Dist: opentelemetry-instrumentation (>=0.52b0,<1.0.0)
Requires-Dist: opentelemetry-instrumentation-aiohttp-client (>=0.52b0,<1.0.0)
Requires-Dist: opentelemetry-instrumentation-asgi (>=0.52b0,<1.0.0)
Requires-Dist: opentelemetry-instrumentation-django (>=0.52b0,<1.0.0)
Requires-Dist: opentelemetry-instrumentation-falcon (>=0.52b0,<1.0.0)
Requires-Dist: opentelemetry-instrumentation-fastapi (>=0.52b0,<1.0.0)
Requires-Dist: opentelemetry-instrumentation-flask (>=0.52b0,<1.0.0)
Requires-Dist: opentelemetry-instrumentation-httpx (>=0.52b0,<1.0.0)
Requires-Dist: opentelemetry-instrumentation-pyramid (>=0.52b0,<1.0.0)
Requires-Dist: opentelemetry-instrumentation-requests (>=0.52b0,<1.0.0)
Requires-Dist: opentelemetry-instrumentation-starlette (>=0.52b0,<1.0.0)
Requires-Dist: opentelemetry-instrumentation-tornado (>=0.52b0,<1.0.0)
Requires-Dist: opentelemetry-instrumentation-urllib (>=0.52b0,<1.0.0)
Requires-Dist: opentelemetry-instrumentation-urllib3 (>=0.52b0,<1.0.0)
Requires-Dist: opentelemetry-sdk (>=1.30.0,<2.0.0)
Requires-Dist: pydantic (>=2.0.0,<3.0.0)
Requires-Dist: requests (>=2.26.0,<3.0.0)
Requires-Dist: schedule (>=1.2.2,<2.0.0)
Requires-Dist: xmltodict (>=0.13.0,<1.0.0)
Project-URL: Homepage, https://github.com/openlit/openlit/tree/main/openlit/python
Project-URL: Repository, https://github.com/openlit/openlit/tree/main/openlit/python
